[
    {
        "nid": "Poisoned",
        "name": "Poisoned",
        "desc": "-20% Def.",
        "icon_nid": "skill_icons",
        "icon_index": [
            6,
            15
        ],
        "components": [
            [
                "negative",
                null
            ],
            [
                "stat_change_expression",
                [
                    [
                        "DEF",
                        "unit.stats.get('DEF') * 2 // 10 * -1"
                    ]
                ]
            ],
            [
                "combined_time",
                4
            ],
            [
                "lost_on_end_chapter",
                null
            ]
        ]
    }
]