[
    {
        "nid": "Stay_of_Execution_S",
        "name": "Stay of Execution",
        "desc": "",
        "icon_nid": "ZessDynamiteSkillsys",
        "icon_index": [
            7,
            7
        ],
        "components": [
            [
                "hidden",
                null
            ],
            [
                "stack",
                999
            ],
            [
                "crit",
                10
            ],
            [
                "lost_on_end_chapter",
                null
            ]
        ]
    }
]