[
    {
        "nid": "2x",
        "name": "Camping Fun",
        "tilemap": "Camping Fun",
        "bg_tilemap": null,
        "party": "Emma",
        "music": {},
        "objective": {
            "simple": "",
            "win": "",
            "loss": ""
        },
        "roam": true,
        "roam_unit": "Emma",
        "go_to_overworld": false,
        "should_record": false,
        "tags": [],
        "units": [
            {
                "nid": "Emma",
                "team": "player",
                "ai": "None",
                "roam_ai": null,
                "ai_group": "",
                "starting_position": [
                    11,
                    4
                ],
                "starting_traveler": null,
                "generic": false
            },
            {
                "nid": "Emily",
                "team": "player",
                "ai": "None",
                "roam_ai": null,
                "ai_group": "",
                "starting_position": [
                    12,
                    4
                ],
                "starting_traveler": null,
                "generic": false
            },
            {
                "nid": "101",
                "variant": null,
                "level": 1,
                "klass": "Tent",
                "faction": "Town_Guard",
                "starting_items": [],
                "starting_skills": [],
                "team": "other",
                "ai": "None",
                "roam_ai": null,
                "ai_group": "",
                "starting_position": [
                    4,
                    4
                ],
                "starting_traveler": null,
                "generic": true
            },
            {
                "nid": "102",
                "variant": null,
                "level": 1,
                "klass": "Tent",
                "faction": "Town_Guard",
                "starting_items": [],
                "starting_skills": [],
                "team": "other",
                "ai": "None",
                "roam_ai": null,
                "ai_group": "",
                "starting_position": [
                    6,
                    10
                ],
                "starting_traveler": null,
                "generic": true
            },
            {
                "nid": "103",
                "variant": null,
                "level": 1,
                "klass": "Tent",
                "faction": "Town_Guard",
                "starting_items": [],
                "starting_skills": [],
                "team": "other",
                "ai": "None",
                "roam_ai": null,
                "ai_group": "",
                "starting_position": [
                    11,
                    6
                ],
                "starting_traveler": null,
                "generic": true
            },
            {
                "nid": "104",
                "variant": null,
                "level": 1,
                "klass": "Tent",
                "faction": "Town_Guard",
                "starting_items": [],
                "starting_skills": [],
                "team": "other",
                "ai": "None",
                "roam_ai": null,
                "ai_group": "",
                "starting_position": [
                    15,
                    4
                ],
                "starting_traveler": null,
                "generic": true
            },
            {
                "nid": "105",
                "variant": null,
                "level": 1,
                "klass": "Tent",
                "faction": "Town_Guard",
                "starting_items": [],
                "starting_skills": [],
                "team": "other",
                "ai": "None",
                "roam_ai": null,
                "ai_group": "",
                "starting_position": [
                    15,
                    9
                ],
                "starting_traveler": null,
                "generic": true
            },
            {
                "nid": "106",
                "variant": null,
                "level": 1,
                "klass": "Torch",
                "faction": "Town_Guard",
                "starting_items": [],
                "starting_skills": [],
                "team": "other",
                "ai": "None",
                "roam_ai": null,
                "ai_group": "",
                "starting_position": [
                    5,
                    4
                ],
                "starting_traveler": null,
                "generic": true
            },
            {
                "nid": "107",
                "variant": null,
                "level": 1,
                "klass": "Torch",
                "faction": "Town_Guard",
                "starting_items": [],
                "starting_skills": [],
                "team": "other",
                "ai": "None",
                "roam_ai": null,
                "ai_group": "",
                "starting_position": [
                    7,
                    10
                ],
                "starting_traveler": null,
                "generic": true
            },
            {
                "nid": "108",
                "variant": null,
                "level": 1,
                "klass": "Torch",
                "faction": "Town_Guard",
                "starting_items": [],
                "starting_skills": [],
                "team": "other",
                "ai": "None",
                "roam_ai": null,
                "ai_group": "",
                "starting_position": [
                    16,
                    4
                ],
                "starting_traveler": null,
                "generic": true
            },
            {
                "nid": "109",
                "variant": null,
                "level": 1,
                "klass": "Torch",
                "faction": "Town_Guard",
                "starting_items": [],
                "starting_skills": [],
                "team": "other",
                "ai": "None",
                "roam_ai": null,
                "ai_group": "",
                "starting_position": [
                    16,
                    9
                ],
                "starting_traveler": null,
                "generic": true
            }
        ],
        "regions": [],
        "unit_groups": [
            {
                "nid": "Cutscene",
                "units": [
                    "Emma",
                    "Emily",
                    "101",
                    "102",
                    "103",
                    "104",
                    "105",
                    "106",
                    "107",
                    "108",
                    "109"
                ],
                "positions": {}
            },
            {
                "nid": "CutsceneA",
                "units": [
                    "Emma",
                    "Emily"
                ],
                "positions": {
                    "Emma": [
                        8,
                        9
                    ],
                    "Emily": [
                        9,
                        9
                    ]
                }
            }
        ],
        "ai_groups": [
            {
                "nid": "",
                "trigger_threshold": 1
            }
        ]
    }
]