[
    {
        "name": "0 - Intro",
        "trigger": "level_start",
        "level_nid": "4",
        "condition": "True",
        "commands": [],
        "only_once": true,
        "priority": 20,
        "_source": [
            "chapter_title",
            "change_background;BlackBackground",
            "music;Advance",
            "speak;;\u2028Gravesoll Port, a town\u2028filled with skilled\u2028sailors and markets\u2028with peculiar goods,{w}\u2028bustles with life\u2028both day and night.{w}\u2028Travelers entering\u2028the port can smell the\u2028ocean on the breeze,{w}\u2028hear the laughter of\u2028the children,{w} and\u2028partake in the music\u2028festivals being held.;;;hint",
            "speak;;\u2028Though, in these\u2028turbulent and\u2028unstable times,{w}\u2028how long can this\u2028little corner of\u2028jubilance survive...?;;;hint",
            "music;Nature Sounds",
            "transition;close",
            "change_background;Outskirts",
            "transition;open",
            "multi_add_portrait;Sarah;FarLeft;Emma;Left;Caroline;Right",
            "speak;Caroline;\u2028Up here should be the\u2028port town of Gravesoll.{w}\u2028I've never been myself,{w}\u2028but I've heard tell of\u2028their markets and festivals.",
            "speak;Emma;\u2028After days of fighting and running,\u2028that would be beyond amazing.",
            "bop_portrait;Emma",
            "expression;Emma;Smile",
            "speak;Emma;\u2028I'm in the perfect mood\u2028to eat and dance all day!",
            "speak;Sarah;\u2028Just a reminder that we're here to\u2028meet Kate and the Dawn Brigade.{w}\u2028The celebrations can happen after\u2028convincing her to join us.",
            "expression;Emma;NoSmile",
            "speak;Caroline;\u2028Trust me, I haven't forgotten.{w}\u2028I would like to show my daughter the\u2028beauty and joy out in the world, though.",
            "speak;Sarah;\u2028It's a commendable endeavor,{w}\u2028though your timing leaves\u2028something to be desired{tgm}...",
            "speak;Caroline;\u2028Maybe, but when your home burns down,{w}\u2028you have to make some sudden and\u2028unexpected choices.{w}\u2028Perhaps you shouldn't make judgements\u2028on things you don't fully understand.",
            "speak;Sarah;\u2028I-I'm sorry, I didn't mean to-",
            "speak;Emma;\u2028How about we all calm down?{w}\u2028Mom, I'm sure Sarah didn't mean\u2028anything negative from her comment.{w}\u2028We're all just a little tense after\u2028having to leave our homes behind.",
            "speak;Sarah;\u2028Yes, maybe I was a little{tgm}...{tgm}\u2028insensitive in my jest.",
            "speak;Emma;\u2028Don't worry, we're all a team now.{w}\u2028We've got to stick together!",
            "speak;Sarah;\u2028Right{tgm}...",
            "speak;Sarah;\u2028It seems I was right about you.{w}\u2028You're already looking to be a\u2028better leader than I am now.",
            "speak;Emma;\u2028Oh please, Sarah, don't be{tgm}...",
            "speak;Emma;\u2028Wait{tgm}...{tgm}{w}{c:bop_portrait;Emma}is that smoke in the sky?",
            "bop_portrait;Caroline",
            "speak;Caroline;\u2028I see flames at the port town!{w}\u2028Everyone, get down while we\u2028move in!{w} We don't want whoever\u2028is attacking to notice us!",
            "multi_remove_portrait;Caroline;Emma;Sarah",
            "end_skip"
        ],
        "nid": "4 0 - Intro"
    }
]